{"cameraMode":{"drawMode":3,"name":"Shadow Cascades","section":"Miscellaneous"},"sceneLighting":true,"audioPlay":false,"sceneViewState":{"showFog":true,"showMaterialUpdate":false,"showSkybox":true,"showFlares":true,"showImageEffects":true,"showParticleSystems":true},"in2DMode":false,"pivot":{"x":-0.048583984375,"y":0.638916015625,"z":-0.3701171875},"rotation":{"x":-0.2820594310760498,"y":-0.4017716646194458,"z":0.13158421218395234,"w":-0.8612245321273804},"size":1.1560062170028687,"orthographic":true}